kedro_partitioned/__init__.py
kedro_partitioned/plugin.py
kedro_partitioned/extras/__init__.py
kedro_partitioned/extras/datasets/__init__.py
kedro_partitioned/extras/datasets/concatenated_dataset.py
kedro_partitioned/extras/datasets/nullable_dataset.py
kedro_partitioned/extras/datasets/threaded_partitioned_dataset.py
kedro_partitioned/extras/datasets/wrapper_dataset.py
kedro_partitioned/io/__init__.py
kedro_partitioned/io/path_safe_partitioned_dataset.py
kedro_partitioned/pipeline/__init__.py
kedro_partitioned/pipeline/multinode.py
kedro_partitioned/pipeline/decorators/__init__.py
kedro_partitioned/pipeline/decorators/decorators.py
kedro_partitioned/pipeline/decorators/helper_factory.py
kedro_partitioned/utils/__init__.py
kedro_partitioned/utils/constants.py
kedro_partitioned/utils/iterable.py
kedro_partitioned/utils/other.py
kedro_partitioned/utils/pipeline.py
kedro_partitioned/utils/string.py
kedro_partitioned/utils/typing.py
kedro_partitioned-0.2.1.dist-info/LICENSE
kedro_partitioned-0.2.1.dist-info/METADATA
kedro_partitioned-0.2.1.dist-info/WHEEL
kedro_partitioned-0.2.1.dist-info/entry_points.txt
kedro_partitioned-0.2.1.dist-info/top_level.txt
kedro_partitioned-0.2.1.dist-info/RECORD
