Metadata-Version: 2.1
Name: kedro-partitioned
Version: 0.2.1
Summary: Kedro plugin extending partitioned dataset support.
Author: Gabriel Daiha Alves
Author-email: Nickolas da Rocha Machado <nickolasrochamachado@gmail.com>
License: Apache License
Classifier: Programming Language :: Python :: 3
Classifier: Operating System :: OS Independent
License-File: LICENSE
Requires-Dist: kedro <0.20,>=0.19
Requires-Dist: kedro-datasets[json,pandas] <4,>=3
Requires-Dist: universal-pathlib <1,>=0.2
Requires-Dist: typing-extensions <5,>=4
